README.rst
setup.cfg
setup.py
dsql/__init__.py
dsql/manager.py
dsql/querybuilder.py
dsql.egg-info/PKG-INFO
dsql.egg-info/SOURCES.txt
dsql.egg-info/dependency_links.txt
dsql.egg-info/top_level.txt