Metadata-Version: 1.1
Name: dsql
Version: 0.4.1
Summary: Dead simple RDBMS handling lib
Home-page: https://github.com/gwn/dsql
Author: gwn
Author-email: egeavunc@gmail.com
License: MIT
Keywords: sql db query builder simple
Platform: UNKNOWN
Classifier: Development Status :: 3 - Alpha
Classifier: Intended Audience :: Developers
Classifier: Topic :: Database
Classifier: License :: OSI Approved :: MIT License
Classifier: Programming Language :: Python :: 2.7
